yandex_gpt/__init__.py
yandex_gpt/iam_getter.py
yandex_gpt/interface.py
yandex_gpt/request_send.py
yandex_gpt/schemas.py
yandex_gpt/settings.py
yandex_gpt-0.3.0.dist-info/METADATA
yandex_gpt-0.3.0.dist-info/WHEEL
yandex_gpt-0.3.0.dist-info/RECORD
