Metadata-Version: 2.1
Name: yandex_gpt
Version: 0.3.0
Summary: Module for simple connecting to YandexGPT Api
Author: vladartemenko
Author-email: skabe99@yandex.ru
Requires-Python: >=3.9,<4.0
Classifier: Programming Language :: Python :: 3
Classifier: Programming Language :: Python :: 3.9
Classifier: Programming Language :: Python :: 3.10
Classifier: Programming Language :: Python :: 3.11
Classifier: Programming Language :: Python :: 3.12
